rocketchat_bot_sdk/__init__.py
rocketchat_bot_sdk/handlers.py
rocketchat_bot_sdk/rocketchat_bot.py
rocketchat_bot_sdk/rocketchat_message.py
rocketchat_bot_sdk/rocketchat_message_listener.py
rocketchat_bot_sdk/rocketchat_async/__init__.py
rocketchat_bot_sdk/rocketchat_async/constants.py
rocketchat_bot_sdk/rocketchat_async/core.py
rocketchat_bot_sdk/rocketchat_async/dispatcher.py
rocketchat_bot_sdk/rocketchat_async/methods.py
rocketchat_bot_sdk-0.0.8.dist-info/LICENSE
rocketchat_bot_sdk-0.0.8.dist-info/METADATA
rocketchat_bot_sdk-0.0.8.dist-info/WHEEL
rocketchat_bot_sdk-0.0.8.dist-info/top_level.txt
rocketchat_bot_sdk-0.0.8.dist-info/RECORD
