Metadata-Version: 2.1
Name: rocketchat-bot-sdk
Version: 0.0.8
Summary: SDK for creating chat bots with the Rocketchat API
Home-page: https://github.com/HappyTetrahedron/rocketchat-bot-sdk
Author: Aline Abler
Author-email: alinea@riseup.net
Classifier: Programming Language :: Python :: 3
Classifier: License :: OSI Approved :: MIT License
Classifier: Operating System :: OS Independent
License-File: LICENSE
Requires-Dist: rocketchat-API
Requires-Dist: websockets (==10.4)
